cursor_mdc_generator/__init__.py
cursor_mdc_generator/cli.py
cursor_mdc_generator/code_summarization.py
cursor_mdc_generator/repo_analyzer.py
cursor_mdc_generator/repository_structure.py
cursor_mdc_generator/symbolic_graph.py
cursor_mdc_generator-0.1.0.dist-info/LICENSE
cursor_mdc_generator-0.1.0.dist-info/METADATA
cursor_mdc_generator-0.1.0.dist-info/WHEEL
cursor_mdc_generator-0.1.0.dist-info/entry_points.txt
cursor_mdc_generator-0.1.0.dist-info/top_level.txt
cursor_mdc_generator-0.1.0.dist-info/RECORD
