Metadata-Version: 2.2
Name: cursor-mdc-generator
Version: 0.1.0
Summary: A tool to generate Cursor IDE MDC files from repository analysis
Author: Cursor MDC Generator
License: MIT
Requires-Python: >=3.7
License-File: LICENSE
Requires-Dist: matplotlib
Requires-Dist: networkx
Requires-Dist: gitpython
Requires-Dist: pygraphviz
Requires-Dist: pydantic
Requires-Dist: astroid
Requires-Dist: openai
Requires-Dist: instructor
Requires-Dist: click
